qa_data/__init__.py
qa_data/agent.py
qa_data-0.1.3.dist-info/METADATA
qa_data-0.1.3.dist-info/WHEEL
qa_data-0.1.3.dist-info/top_level.txt
qa_data-0.1.3.dist-info/RECORD
